aih/__init__.py
aih/aih.py
aih-0.1.1.dist-info/METADATA
aih-0.1.1.dist-info/WHEEL
aih-0.1.1.dist-info/top_level.txt
aih-0.1.1.dist-info/RECORD
