Metadata-Version: 2.1
Name: aih
Version: 0.1.1
Summary: UNKNOWN
Home-page: UNKNOWN
Author: huy.ha
Author-email: huy.ha@vmodev.com
License: MIT
Platform: UNKNOWN
Requires-Dist: PyJWT
Requires-Dist: requests
